ARIclicker
