Metadata-Version: 2.1
Name: ARIclicker
Version: 2.0.1
Summary: The best autoclicker in minecraft!
Home-page: UNKNOWN
Author: LIN,Zhe
Author-email: 2081812728@qq.com
License: MIT
Keywords: autoclicker,minecraft-auto
Platform: UNKNOWN
Classifier: Development Status :: 5 - Production/Stable
Classifier: Intended Audience :: Education
Classifier: Operating System :: Microsoft :: Windows :: Windows 10
Classifier: License :: OSI Approved :: MIT License
Classifier: Programming Language :: Python :: 3
Requires: pynput
